pi/__init__.py
pi/pi.py
pi/pi_httpx.py
pi/proxies.py
pi/test.py
inflection_pi_api-0.1.3.dist-info/LICENSE
inflection_pi_api-0.1.3.dist-info/METADATA
inflection_pi_api-0.1.3.dist-info/WHEEL
inflection_pi_api-0.1.3.dist-info/top_level.txt
inflection_pi_api-0.1.3.dist-info/RECORD
