Metadata-Version: 2.1
Name: inflection-pi-api
Version: 0.1.3
Summary: A reverse engineered API for Inflection AI Personal Intelligence, called PI
Home-page: https://github.com/hansfzlorenzana/Inflection-Pi-API
Author: Hans FZ Lorenzana
Project-URL: Bug Report, https://github.com/hansfzlorenzana/Inflection-Pi-API/issues/new
Keywords: python,pi-api,inflection,chatgpt,pi,ai,api,chatbot
Classifier: Programming Language :: Python :: 3
Classifier: Intended Audience :: Developers
Classifier: Topic :: Software Development :: Libraries :: Python Modules
Classifier: License :: OSI Approved :: MIT License
Classifier: Operating System :: OS Independent
Requires-Python: >=3.7
License-File: LICENSE
Requires-Dist: httpx
Requires-Dist: websocket-client
Requires-Dist: requests-toolbelt
Requires-Dist: loguru
Provides-Extra: proxy
Requires-Dist: ballyregan ; (python_version >= "3.9") and extra == 'proxy'
